adafruit_ssd1608.py
adafruit_circuitpython_ssd1608-1.3.8.dist-info/licenses/LICENSE
adafruit_circuitpython_ssd1608-1.3.8.dist-info/METADATA
adafruit_circuitpython_ssd1608-1.3.8.dist-info/WHEEL
adafruit_circuitpython_ssd1608-1.3.8.dist-info/top_level.txt
adafruit_circuitpython_ssd1608-1.3.8.dist-info/RECORD
